cuisto/__init__.py
cuisto/atlas.py
cuisto/compute.py
cuisto/config.py
cuisto/display.py
cuisto/io.py
cuisto/process.py
cuisto/segmentation.py
cuisto/utils.py
cuisto-2025.6.17.dist-info/METADATA
cuisto-2025.6.17.dist-info/WHEEL
cuisto-2025.6.17.dist-info/licenses/LICENSE
cuisto-2025.6.17.dist-info/RECORD
