Metadata-Version: 2.4
Name: cuisto
Version: 2025.6.17
Summary: Quantification of objects in histological slices
Project-URL: Source Code, https://github.com/TeamNCMC/cuisto
Author-email: Guillaume Le Goc <g.legoc@posteo.org>
License: MIT
License-File: LICENSE
Classifier: Programming Language :: Python :: 3.12
Classifier: Programming Language :: Python :: 3.13
Requires-Python: >=3.12
Requires-Dist: brainglobe-atlasapi>=2.0.7
Requires-Dist: brainglobe-heatmap>=0.5.4
Requires-Dist: brainrender>=2.1.14
Requires-Dist: geojson>=3.1.0
Requires-Dist: h5py>=3.11
Requires-Dist: ipykernel
Requires-Dist: ipympl
Requires-Dist: ipywidgets
Requires-Dist: matplotlib>=3.9.0
Requires-Dist: notebook>=7
Requires-Dist: numpy>=2
Requires-Dist: orjson>=3.10.3
Requires-Dist: pandas[performance]>2.2.2
Requires-Dist: requests
Requires-Dist: scikit-image>0.22.0
Requires-Dist: seaborn>=0.13.2
Requires-Dist: shapely>=2.0.4
Requires-Dist: skan>=0.12.0
Requires-Dist: tables>=3.10.1
Requires-Dist: tifffile>=2024.4.24
Requires-Dist: tqdm
Requires-Dist: typer
Provides-Extra: dev
Requires-Dist: pytest; extra == 'dev'
Requires-Dist: pytest-cov; extra == 'dev'
Provides-Extra: doc
Requires-Dist: mkdocs; extra == 'doc'
Requires-Dist: mkdocs-git-revision-date-localized-plugin; extra == 'doc'
Requires-Dist: mkdocs-jupyter; extra == 'doc'
Requires-Dist: mkdocs-material; extra == 'doc'
Requires-Dist: mkdocstrings; extra == 'doc'
Requires-Dist: mkdocstrings-python; extra == 'doc'
